google_sheets_telegram_utils/__init__.py
google_sheets_telegram_utils/exceptions.py
google_sheets_telegram_utils/examples/__init__.py
google_sheets_telegram_utils/handlers/__init__.py
google_sheets_telegram_utils/handlers/testing_handlers.py
google_sheets_telegram_utils/presets/__init__.py
google_sheets_telegram_utils/presets/abstract_job.py
google_sheets_telegram_utils/presets/inline_keyboard.py
google_sheets_telegram_utils/presets/main_example.py
google_sheets_telegram_utils/tests/__init__.py
google_sheets_telegram_utils/tests/test_csv_connector.py
google_sheets_telegram_utils/tests/test_google_sheet_connector.py
google_sheets_telegram_utils/tests/test_telegram_user.py
google_sheets_telegram_utils/utils/__init__.py
google_sheets_telegram_utils/utils/active_user_decorator.py
google_sheets_telegram_utils/utils/classes/__init__.py
google_sheets_telegram_utils/utils/classes/telegram_user.py
google_sheets_telegram_utils/utils/configs/__init__.py
google_sheets_telegram_utils/utils/configs/abstract_config.py
google_sheets_telegram_utils/utils/configs/csv_config.py
google_sheets_telegram_utils/utils/configs/google_sheet_config.py
google_sheets_telegram_utils/utils/connectors/__init__.py
google_sheets_telegram_utils/utils/connectors/abstract_connector.py
google_sheets_telegram_utils/utils/connectors/csv_connector.py
google_sheets_telegram_utils/utils/connectors/google_sheet_connector.py
google_sheets_telegram_utils/utils/factories/__init__.py
google_sheets_telegram_utils/utils/factories/handlers_factory.py
google_sheets_telegram_utils-0.1.1.dist-info/licenses/LICENSE
google_sheets_telegram_utils-0.1.1.dist-info/METADATA
google_sheets_telegram_utils-0.1.1.dist-info/WHEEL
google_sheets_telegram_utils-0.1.1.dist-info/top_level.txt
google_sheets_telegram_utils-0.1.1.dist-info/RECORD
