Metadata-Version: 2.4
Name: google-sheets-telegram-utils
Version: 0.1.1
Summary: A package with utils to work with google spreadsheet and telegram bots
Home-page: https://github.com/alexVarkalov/google_sheets_telegram_utils
Author: Alexander Varkalov
Author-email: alex.varkalov@gmail.com
License: BSD 2-clause
Classifier: Development Status :: 1 - Planning
Classifier: Environment :: Other Environment
Classifier: Intended Audience :: Science/Research
Classifier: License :: OSI Approved :: BSD License
Classifier: Operating System :: POSIX :: Linux
Classifier: Programming Language :: Python :: 3.10
License-File: LICENSE
Requires-Dist: python-telegram-bot==22.4
Requires-Dist: python-dotenv==1.1.1
Requires-Dist: google-api-python-client==2.183.0
Requires-Dist: google-auth-oauthlib==1.2.2
Requires-Dist: gspread==6.2.1
Dynamic: author
Dynamic: author-email
Dynamic: classifier
Dynamic: home-page
Dynamic: license
Dynamic: license-file
Dynamic: requires-dist
Dynamic: summary
